[{"Hour":0,"TotalTransactions":42},{"Hour":1,"TotalTransactions":34},{"Hour":2,"TotalTransactions":37},{"Hour":3,"TotalTransactions":51},{"Hour":4,"TotalTransactions":44},{"Hour":5,"TotalTransactions":33},{"Hour":6,"TotalTransactions":39},{"Hour":7,"TotalTransactions":45},{"Hour":8,"TotalTransactions":35},{"Hour":9,"TotalTransactions":48},{"Hour":10,"TotalTransactions":42},{"Hour":11,"TotalTransactions":39},{"Hour":12,"TotalTransactions":37},{"Hour":13,"TotalTransactions":30},{"Hour":14,"TotalTransactions":60},{"Hour":15,"TotalTransactions":36},{"Hour":16,"TotalTransactions":51},{"Hour":17,"TotalTransactions":47},{"Hour":18,"TotalTransactions":42},{"Hour":19,"TotalTransactions":45},{"Hour":20,"TotalTransactions":39},{"Hour":21,"TotalTransactions":41},{"Hour":22,"TotalTransactions":46},{"Hour":23,"TotalTransactions":37}]